umami/__init__.py
umami/_version.py
umami/metric.py
umami/residual.py
umami/calculations/__init__.py
umami/calculations/metric/__init__.py
umami/calculations/metric/aggregate.py
umami/calculations/metric/chi_intercept_gradient.py
umami/calculations/metric/count_equal.py
umami/calculations/metric/hypsometric_integral.py
umami/calculations/metric/mask_aggregation.py
umami/calculations/metric/watershed_aggregation.py
umami/calculations/residual/__init__.py
umami/calculations/residual/discretized_misfit.py
umami/calculations/residual/joint_density_misfit.py
umami/calculations/residual/kstest.py
umami/utils/__init__.py
umami/utils/create_landlab_components.py
umami/utils/io.py
umami/utils/validate.py
umami-2.0.0.dist-info/LICENSE
umami-2.0.0.dist-info/METADATA
umami-2.0.0.dist-info/WHEEL
umami-2.0.0.dist-info/top_level.txt
umami-2.0.0.dist-info/RECORD
