Metadata-Version: 2.1
Name: umami
Version: 2.0.0
Summary: Umami calculates landscape metrics
Home-page: https://github.com/TerrainBento/umami/
Author: Katy Barnhart
Author-email: barnhark@colorado.edu
License: MIT
Platform: UNKNOWN
Classifier: Intended Audience :: Science/Research
Classifier: License :: OSI Approved :: MIT License
Classifier: Operating System :: OS Independent
Classifier: Programming Language :: Python :: 3.4
Classifier: Programming Language :: Python :: 3.5
Classifier: Programming Language :: Python :: 3.6
Classifier: Programming Language :: Python :: 3.7
Classifier: Programming Language :: Python :: Implementation :: CPython
Classifier: Topic :: Scientific/Engineering :: Physics
Requires-Python: >=3
Requires-Dist: scipy
Requires-Dist: numpy
Requires-Dist: landlab (>=2.0.0b4)
